cachalot/__init__.py
cachalot/api.py
cachalot/apps.py
cachalot/cache.py
cachalot/jinja2ext.py
cachalot/models.py
cachalot/monkey_patch.py
cachalot/panels.py
cachalot/settings.py
cachalot/signals.py
cachalot/transaction.py
cachalot/utils.py
cachalot/management/__init__.py
cachalot/management/commands/__init__.py
cachalot/management/commands/invalidate_cachalot.py
cachalot/templates/cachalot/panel.html
cachalot/templatetags/__init__.py
cachalot/templatetags/cachalot.py
cachalot/tests/__init__.py
cachalot/tests/api.py
cachalot/tests/db_router.py
cachalot/tests/debug_toolbar.py
cachalot/tests/loaddata_fixture.json
cachalot/tests/models.py
cachalot/tests/multi_db.py
cachalot/tests/postgres.py
cachalot/tests/read.py
cachalot/tests/settings.py
cachalot/tests/signals.py
cachalot/tests/test_utils.py
cachalot/tests/thread_safety.py
cachalot/tests/transaction.py
cachalot/tests/write.py
cachalot/tests/migrations/0001_initial.py
cachalot/tests/migrations/__init__.py
lc_django_cachalot-2.1.3.dist-info/LICENSE
lc_django_cachalot-2.1.3.dist-info/METADATA
lc_django_cachalot-2.1.3.dist-info/WHEEL
lc_django_cachalot-2.1.3.dist-info/top_level.txt
lc_django_cachalot-2.1.3.dist-info/RECORD
